datorama/__init__.py
datorama/datorama.py
datorama-0.8.dist-info/METADATA
datorama-0.8.dist-info/RECORD
datorama-0.8.dist-info/WHEEL
datorama-0.8.dist-info/top_level.txt
