Metadata-Version: 2.1
Name: datorama
Version: 0.8
Summary: Datorama Python Package
Home-page: https://github.com/datorama/python-connector-package
Author: Asaad Awesat
Author-email: asaad.awesat@datorama.com
License: MIT
Platform: UNKNOWN
